MANIFEST.in
README.md
setup.cfg
setup.py
TOPSIS_Chirag_101803366/topsis.py
TOPSIS_Chirag_101803366.egg-info/PKG-INFO
TOPSIS_Chirag_101803366.egg-info/SOURCES.txt
TOPSIS_Chirag_101803366.egg-info/dependency_links.txt
TOPSIS_Chirag_101803366.egg-info/entry_points.txt
TOPSIS_Chirag_101803366.egg-info/requires.txt
TOPSIS_Chirag_101803366.egg-info/top_level.txt