Metadata-Version: 2.1
Name: TOPSIS-Chirag-101803366
Version: 1.0
Summary: A Python package implementing TOPSIS technique.
Home-page: UNKNOWN
Author: Chirag Jain
Author-email: cjain_be18@thapar.edu
License: MIT
Platform: UNKNOWN
Classifier: License :: OSI Approved :: MIT License
Classifier: Programming Language :: Python :: 3
Classifier: Programming Language :: Python :: 3.7
